[
 {
  "table":"DDTYPES",
  "data":
  [
   {
    "TYPENAME":"ZIF_CTS_COMM_001",
    "STATE":"A",
    "TYPEKIND":"INTF"
   }
  ]
 },
 {
  "table":"SEOCLASS",
  "data":
  [
   {
    "CLSNAME":"ZIF_CTS_COMM_001",
    "CLSTYPE":1,
    "UUID":"J/FFEeGQHt+HrGnP1v1G5w==",
    "REMOTE":""
   }
  ]
 },
 {
  "table":"SEOCLASSDF",
  "data":
  [
   {
    "CLSNAME":"ZIF_CTS_COMM_001",
    "VERSION":1,
    "CATEGORY":0,
    "EXPOSURE":2,
    "STATE":1,
    "RELEASE":0,
    "AUTHOR":"",
    "CREATEDON":"2024-05-29",
    "CHANGEDBY":"",
    "CHANGEDON":"0000-00-00",
    "CHGDANYBY":"",
    "CHGDANYON":"0000-00-00",
    "CLSEMBED":"",
    "CLSABSTRCT":"",
    "CLSFINAL":"",
    "CLSCCINCL":"",
    "CLSDEFATT":"",
    "CLSDEFMTD":"",
    "REFCLSNAME":"",
    "FIXPT":"",
    "VARCL":"",
    "UNICODE":"5",
    "RSTAT":"",
    "CLSBCIMPL":"",
    "R3RELEASE":"795",
    "CLSBCTRANS":"",
    "CLSBCCAT":0,
    "CLSBCNODEL":"",
    "CLSADDON":"",
    "MSG_ID":"",
    "CLSPROXY":"",
    "CLSSHAREDMEMORY":"",
    "WITH_UNIT_TESTS":"",
    "DURATION_TYPE":"0",
    "RISK_LEVEL":"0",
    "WITHIN_PACKAGE":""
   }
  ]
 },
 {
  "table":"SEOCLASSTX",
  "data":
  [
   {
    "CLSNAME":"ZIF_CTS_COMM_001",
    "LANGU":"E",
    "DESCRIPT":"Comm Interface 001"
   }
  ]
 },
 {
  "table":"TADIR",
  "data":
  [
   {
    "PGMID":"R3TR",
    "OBJECT":"INTF",
    "OBJ_NAME":"ZIF_CTS_COMM_001",
    "KORRNUM":"",
    "SRCSYSTEM":"...",
    "AUTHOR":"SAP_CUSTOMER",
    "SRCDEP":"",
    "DEVCLASS":"ZCTS_COMM_001",
    "GENFLAG":"",
    "EDTFLAG":"",
    "CPROJECT":" L",
    "MASTERLANG":"E",
    "VERSID":"",
    "PAKNOCHECK":"",
    "OBJSTABLTY":"",
    "COMPONENT":"",
    "CRELEASE":"",
    "DELFLAG":"",
    "TRANSLTTXT":"",
    "CREATED_ON":"2024-05-29",
    "CHECK_DATE":"2024-05-29",
    "CHECK_CFG":""
   }
  ]
 },
 {
  "table":"TRDIR",
  "data":
  [
   {
    "NAME":"ZIF_CTS_COMM_001==============IP",
    "VARCL":"X",
    "DBAPL":"S",
    "DBNA":"D$",
    "SUBC":"J",
    "APPL":"S",
    "FIXPT":"X",
    "LDBNAME":"D$S",
    "UCCHECK":"5"
   },
   {
    "NAME":"ZIF_CTS_COMM_001==============IT",
    "DBAPL":"S",
    "DBNA":"D$",
    "SUBC":"I",
    "APPL":"S",
    "FIXPT":"X",
    "LDBNAME":"D$S",
    "UCCHECK":"X"
   },
   {
    "NAME":"ZIF_CTS_COMM_001==============IU",
    "VARCL":"X",
    "DBAPL":"S",
    "DBNA":"D$",
    "SUBC":"I",
    "APPL":"S",
    "FIXPT":"X",
    "LDBNAME":"D$S",
    "UCCHECK":"X"
   }
  ]
 }
]